invenio_i18n/__init__.py
invenio_i18n/babel.py
invenio_i18n/cli.py
invenio_i18n/config.py
invenio_i18n/ext.py
invenio_i18n/jinja2.py
invenio_i18n/proxies.py
invenio_i18n/selectors.py
invenio_i18n/views.py
invenio_i18n/webpack.py
invenio_i18n/assets/bootstrap3/js/invenio_i18n/app.js
invenio_i18n/assets/semantic-ui/js/invenio_i18n/app.js
invenio_i18n/templates/invenio_i18n/macros/language_selector.html
invenio_i18n/templates/semantic-ui/invenio_i18n/macros/language_selector.html
invenio_i18n/translations/messages.pot
invenio_i18n/translations/ar/LC_MESSAGES/messages.mo
invenio_i18n/translations/ar/LC_MESSAGES/messages.po
invenio_i18n/translations/bg/LC_MESSAGES/messages.mo
invenio_i18n/translations/bg/LC_MESSAGES/messages.po
invenio_i18n/translations/ca/LC_MESSAGES/messages.mo
invenio_i18n/translations/ca/LC_MESSAGES/messages.po
invenio_i18n/translations/cs/LC_MESSAGES/messages.mo
invenio_i18n/translations/cs/LC_MESSAGES/messages.po
invenio_i18n/translations/da/LC_MESSAGES/messages.mo
invenio_i18n/translations/da/LC_MESSAGES/messages.po
invenio_i18n/translations/de/LC_MESSAGES/messages.mo
invenio_i18n/translations/de/LC_MESSAGES/messages.po
invenio_i18n/translations/el/LC_MESSAGES/messages.mo
invenio_i18n/translations/el/LC_MESSAGES/messages.po
invenio_i18n/translations/en/LC_MESSAGES/messages.mo
invenio_i18n/translations/en/LC_MESSAGES/messages.po
invenio_i18n/translations/es/LC_MESSAGES/messages.mo
invenio_i18n/translations/es/LC_MESSAGES/messages.po
invenio_i18n/translations/et/LC_MESSAGES/messages.mo
invenio_i18n/translations/et/LC_MESSAGES/messages.po
invenio_i18n/translations/fa/LC_MESSAGES/messages.mo
invenio_i18n/translations/fa/LC_MESSAGES/messages.po
invenio_i18n/translations/fi/LC_MESSAGES/messages.mo
invenio_i18n/translations/fi/LC_MESSAGES/messages.po
invenio_i18n/translations/fr/LC_MESSAGES/messages.mo
invenio_i18n/translations/fr/LC_MESSAGES/messages.po
invenio_i18n/translations/hr/LC_MESSAGES/messages.mo
invenio_i18n-3.4.3.dist-info/licenses/AUTHORS.rst
invenio_i18n-3.4.3.dist-info/licenses/LICENSE
invenio_i18n-3.4.3.dist-info/METADATA
invenio_i18n-3.4.3.dist-info/WHEEL
invenio_i18n-3.4.3.dist-info/entry_points.txt
invenio_i18n-3.4.3.dist-info/top_level.txt
invenio_i18n-3.4.3.dist-info/RECORD
