Metadata-Version: 2.4
Name: invenio-i18n
Version: 3.4.3
Summary: Invenio internationalization (I18N) module.
Home-page: https://github.com/inveniosoftware/invenio-i18n
Author: CERN
Author-email: info@inveniosoftware.org
License: MIT
Keywords: invenio internationalization i18n localization l10n
Platform: any
Classifier: Development Status :: 5 - Production/Stable
Requires-Python: >=3.7
License-File: LICENSE
License-File: AUTHORS.rst
Requires-Dist: Babel>=2.8
Requires-Dist: Flask-Babel>=3.0.0
Requires-Dist: invenio-base<3.0.0,>=2.3.0
Requires-Dist: pytz<2024.2
Requires-Dist: polib>=1.2.0
Provides-Extra: tests
Requires-Dist: invenio-assets<5.0.0,>=4.0.0; extra == "tests"
Requires-Dist: Flask-Login>=0.6.2; extra == "tests"
Requires-Dist: pytest-black-ng>=0.4.0; extra == "tests"
Requires-Dist: pytest-invenio<4.0.0,>=3.0.0; extra == "tests"
Requires-Dist: sphinx>=4.5; extra == "tests"
Dynamic: license-file
